rj2y/__init__.py
rj2y/main.py
rj2y-0.1.5.dist-info/METADATA
rj2y-0.1.5.dist-info/WHEEL
rj2y-0.1.5.dist-info/entry_points.txt
rj2y-0.1.5.dist-info/RECORD
